scrapy_sentry_sdk/__init__.py
scrapy_sentry_sdk/extensions.py
scrapy_sentry_sdk-0.4.1.dist-info/WHEEL
scrapy_sentry_sdk-0.4.1.dist-info/METADATA
scrapy_sentry_sdk-0.4.1.dist-info/RECORD
