Metadata-Version: 2.1
Name: scrapy-sentry-sdk
Version: 0.4.1
Summary: Scrapy extension for integration of Sentry SDK to Scrapy projects
Home-page: https://github.com/groupbwt/scrapy-sentry-sdk/
License: MIT
Keywords: Error reporting,Monitoring,Scrapy,Sentry
Author: KristobalJunta
Author-email: junta.kristobal@gmail.com
Requires-Python: >=3.6,<4.0
Classifier: License :: OSI Approved :: MIT License
Classifier: Programming Language :: Python :: 3
Classifier: Programming Language :: Python :: 3.6
Classifier: Programming Language :: Python :: 3.7
Classifier: Programming Language :: Python :: 3.8
Classifier: Topic :: Software Development :: Libraries :: Python Modules
Requires-Dist: scrapy (>=1.6,<2.0)
Requires-Dist: sentry-sdk (>=0.19,<0.20)
Project-URL: Repository, https://github.com/groupbwt/scrapy-sentry-sdk/
